<?xml version="1.0" encoding="utf-8"?>
<sketch id="5082a797-ea71-48df-b372-701a122e9278" units="pixel">
  <point x="369.1724" y="228.6664" pressure="0.1411765" time="1310684127489" name="point" id="8ac0ad92-13d6-4918-a979-ed379ebf4756" />
  <point x="369.7562" y="228.8058" pressure="0.282353" time="1310684127497" name="point" id="56a0553a-f1dd-436e-96ad-c43a139652b8" />
  <point x="370.6513" y="229.1312" pressure="0.427451" time="1310684127504" name="point" id="0207b49d-0d63-4618-986d-4bd1dc44b079" />
  <point x="371.7799" y="229.8286" pressure="0.5647059" time="1310684127512" name="point" id="1b7026ef-c82f-4d18-ae58-246cc377d875" />
  <point x="373.0252" y="230.8048" pressure="0.5607843" time="1310684127519" name="point" id="5e25e478-5249-4a7e-b98d-34269ce4db56" />
  <point x="374.8155" y="232.153" pressure="0.5568628" time="1310684127527" name="point" id="8f13619d-52b4-486a-9069-e24053eb089c" />
  <point x="376.9948" y="233.8266" pressure="0.5568628" time="1310684127534" name="point" id="04d1a15f-874d-4331-8452-958b55f391b4" />
  <point x="379.5245" y="235.8722" pressure="0.5607843" time="1310684127542" name="point" id="c932b69f-dc21-43ae-9304-0070165cf38f" />
  <point x="382.2876" y="238.2896" pressure="0.5607843" time="1310684127549" name="point" id="124ccc8b-5deb-4f18-a2ae-3dee9183d2ee" />
  <point x="385.1675" y="241.0789" pressure="0.5607843" time="1310684127557" name="point" id="0d566dcc-8071-4d73-93d3-b2ce53c9f014" />
  <point x="388.0085" y="244.2402" pressure="0.5647059" time="1310684127564" name="point" id="864f83c7-d6f7-454d-bc27-5054ae046c6a" />
  <point x="390.8884" y="247.7734" pressure="0.5686275" time="1310684127572" name="point" id="88cc4dcc-2e92-413d-a3f1-57d916918a4a" />
  <point x="393.6126" y="251.7249" pressure="0.572549" time="1310684127580" name="point" id="b16f2160-0207-4dfc-8ed2-d677851c7728" />
  <point x="396.0255" y="255.9554" pressure="0.5803922" time="1310684127587" name="point" id="aae2dcd2-bf04-4462-8edf-13a09e053e9a" />
  <point x="398.2049" y="260.6044" pressure="0.5843138" time="1310684127595" name="point" id="cf9ea51d-76d3-4205-af62-2b06ba57c429" />
  <point x="399.9562" y="265.3927" pressure="0.5882353" time="1310684127602" name="point" id="c7ae6848-c2c5-44b8-95a6-1102421166e5" />
  <point x="401.3962" y="270.5995" pressure="0.6" time="1310684127610" name="point" id="9fe08c9b-38a9-4fdb-b9ab-19adef133396" />
  <point x="402.408" y="276.0387" pressure="0.6078432" time="1310684127617" name="point" id="5b988c8e-735f-463c-83db-7afc92ef803f" />
  <point x="403.1475" y="281.7569" pressure="0.6156863" time="1310684127625" name="point" id="def14125-a4c2-420a-a869-ba42c82f6364" />
  <point x="403.342" y="287.4286" pressure="0.6235294" time="1310684127632" name="point" id="5b53db60-2035-49e3-8167-f8e3bb47330b" />
  <point x="403.3031" y="293.2397" pressure="0.6313726" time="1310684127640" name="point" id="468f5237-92d4-46bc-85d1-e1314cd41474" />
  <point x="402.7972" y="298.9579" pressure="0.6352941" time="1310684127647" name="point" id="dae99083-ceac-4eea-9786-63b9bc73f5c2" />
  <point x="402.0578" y="304.676" pressure="0.6431373" time="1310684127655" name="point" id="204893ad-24a3-4f29-b331-1620cd81f51a" />
  <point x="401.007" y="310.1153" pressure="0.6470588" time="1310684127662" name="point" id="486838c9-0db7-4c86-ab16-082a9567e62c" />
  <point x="399.7227" y="315.3685" pressure="0.6509804" time="1310684127670" name="point" id="3cb90ef2-358a-4018-a89b-e187f753180a" />
  <point x="398.2438" y="320.1104" pressure="0.654902" time="1310684127677" name="point" id="5760e1e6-c06d-48fc-9e13-c1444bb28624" />
  <point x="396.6482" y="324.5269" pressure="0.654902" time="1310684127685" name="point" id="b7cb44db-1bee-4dca-9309-afc3b4ece21e" />
  <point x="394.9748" y="328.3855" pressure="0.654902" time="1310684127692" name="point" id="a66e5009-b191-492d-8d38-dbb50398bd2a" />
  <point x="393.3013" y="331.7792" pressure="0.654902" time="1310684127700" name="point" id="ddbeef94-e300-4766-bd36-2ca0687aeebc" />
  <point x="391.7057" y="334.6615" pressure="0.6509804" time="1310684127707" name="point" id="4716ed65-6a05-485e-892d-7d14c87439bd" />
  <point x="390.2268" y="336.9395" pressure="0.6470588" time="1310684127715" name="point" id="0ad5d0fc-8084-463f-9a94-7b3689fef78c" />
  <point x="389.0204" y="338.7525" pressure="0.6431373" time="1310684127722" name="point" id="7d67a197-6452-49ff-ba2f-c7e266512c7e" />
  <point x="387.9307" y="340.0542" pressure="0.627451" time="1310684127730" name="point" id="963d8cb2-8d28-47dd-af75-17149c02c3a6" />
  <point x="387.1913" y="341.17" pressure="0.5960785" time="1310684127737" name="point" id="a32a3bd9-3820-451d-bfed-0847c84d027e" />
  <point x="386.2183" y="341.6814" pressure="0.4470588" time="1310684127745" name="point" id="91b639ae-6e4a-4df0-b054-8cebf8bf8c64" />
  <point x="385.8291" y="341.8208" pressure="0.2862745" time="1310684127752" name="point" id="450679cb-2b58-45d4-bbe1-9d063fe757aa" />
  <point x="385.8291" y="341.8208" pressure="0.1333333" time="1310684127760" name="point" id="41a4d93f-9833-4f4e-b8a1-0fde367878f5" />
  <point x="406.2609" y="235.4538" pressure="0.04313726" time="1310684128193" name="point" id="6b58b7c7-3e93-4e2f-b31e-788d957842db" />
  <point x="407.0392" y="235.7327" pressure="0.1764706" time="1310684128201" name="point" id="76014bfe-f310-4067-8f8f-a506da1c7c4a" />
  <point x="407.8565" y="236.2441" pressure="0.3098039" time="1310684128208" name="point" id="3197158c-0640-4656-ae56-44b8cb8a9bc3" />
  <point x="408.8294" y="237.0344" pressure="0.4431373" time="1310684128216" name="point" id="ffb03809-4660-426f-8543-0148f4e50da5" />
  <point x="410.0359" y="238.1501" pressure="0.4784314" time="1310684128223" name="point" id="db3d1105-f5f1-440e-95a2-36b06519a48b" />
  <point x="411.4369" y="239.7307" pressure="0.4823529" time="1310684128231" name="point" id="3127eace-932a-4182-9d5c-5e7b42fabc66" />
  <point x="412.9936" y="241.5903" pressure="0.4941176" time="1310684128238" name="point" id="f9e965d6-b195-4c45-a099-d8df1c719fb5" />
  <point x="414.7838" y="243.9148" pressure="0.5019608" time="1310684128246" name="point" id="f9973aec-f22a-4d4e-85af-25299f559f3a" />
  <point x="416.6129" y="246.5647" pressure="0.5137255" time="1310684128253" name="point" id="394fd5e9-ba1e-4ce1-8ed5-f8ed36eb5666" />
  <point x="418.5977" y="249.7259" pressure="0.5215687" time="1310684128261" name="point" id="70908f5e-7562-46ee-b973-83466d7d1b3c" />
  <point x="420.4658" y="253.1196" pressure="0.5294118" time="1310684128268" name="point" id="d5dc8a7b-a28a-467f-889d-fc6efe6c2057" />
  <point x="422.4117" y="256.9317" pressure="0.5372549" time="1310684128276" name="point" id="5e1f6087-6419-4011-8f08-c5572fe559aa" />
  <point x="424.2408" y="260.9763" pressure="0.5450981" time="1310684128283" name="point" id="8d992c52-fd53-4df6-8cbb-9a88cdadc5fa" />
  <point x="426.0699" y="265.3927" pressure="0.5568628" time="1310684128291" name="point" id="e062116d-6f21-4243-bbc7-50bb52ff92c2" />
  <point x="427.6266" y="269.9951" pressure="0.5686275" time="1310684128299" name="point" id="8a53321f-569b-48b4-8414-99ef0567657d" />
  <point x="429.1055" y="275.016" pressure="0.5803922" time="1310684128306" name="point" id="f31eb700-b939-4e45-9a8a-4498ad95430f" />
  <point x="430.1563" y="280.2227" pressure="0.5921569" time="1310684128314" name="point" id="2dcb1266-27e3-460c-88b6-ca10757fcd07" />
  <point x="431.0125" y="285.7085" pressure="0.6" time="1310684128321" name="point" id="71bf2983-71b8-42dc-8839-6431bb4ab685" />
  <point x="431.4016" y="291.1942" pressure="0.6078432" time="1310684128329" name="point" id="eae13b6d-0cfb-4d3a-b5f2-bdacff4f73cb" />
  <point x="431.5184" y="297.0053" pressure="0.6156863" time="1310684128336" name="point" id="10649d4c-692a-4cc1-8f71-1a8589548504" />
  <point x="431.0903" y="302.7235" pressure="0.6235294" time="1310684128344" name="point" id="31139d15-d155-4fd0-8633-a9377fa648fd" />
  <point x="430.312" y="308.4417" pressure="0.627451" time="1310684128351" name="point" id="bfb60657-80e1-4fab-a6c0-fa19d84bc4f8" />
  <point x="429.0666" y="313.9738" pressure="0.627451" time="1310684128359" name="point" id="84495c1f-3194-4e07-a603-68956e919786" />
  <point x="427.5488" y="319.3201" pressure="0.627451" time="1310684128366" name="point" id="1aac4ce3-f33f-49a1-bc68-ab1db3a596c1" />
  <point x="425.7197" y="324.2014" pressure="0.6313726" time="1310684128374" name="point" id="2396b052-fdaf-412c-b4bf-7d20391acb72" />
  <point x="423.7738" y="328.6644" pressure="0.6352941" time="1310684128381" name="point" id="8e5eeda2-0d3d-4d29-a6c1-129909a5fbbe" />
  <point x="421.7501" y="332.709" pressure="0.6352941" time="1310684128389" name="point" id="3876ac93-b5f0-4ede-9b7d-bc7c42258625" />
  <point x="419.8042" y="336.1491" pressure="0.6352941" time="1310684128396" name="point" id="41041554-f31d-4acb-89c6-0de668f44c20" />
  <point x="417.9751" y="339.078" pressure="0.6352941" time="1310684128404" name="point" id="fa311aed-4412-4c08-a0ba-c7ec992eeb28" />
  <point x="416.3795" y="341.5419" pressure="0.6352941" time="1310684128411" name="point" id="6bc83ab8-b08b-4c6d-b356-43d0c43800d8" />
  <point x="415.0562" y="343.4944" pressure="0.6313726" time="1310684128419" name="point" id="2048c31e-e256-46f4-9f99-44b071dc7aa9" />
  <point x="414.0055" y="344.9821" pressure="0.6352941" time="1310684128426" name="point" id="54cfa7d6-7037-437f-a497-42673928121e" />
  <point x="413.2661" y="346.0978" pressure="0.6313726" time="1310684128434" name="point" id="e02695e8-1c1f-4a6d-9206-0ea28e6a432a" />
  <point x="412.7212" y="346.7487" pressure="0.6235294" time="1310684128441" name="point" id="0f5b3433-e00f-4912-b4d1-7b6b60b47dc2" />
  <point x="412.5266" y="347.26" pressure="0.6" time="1310684128449" name="point" id="1a4b4ef6-109c-4097-8536-fbd562ad5b92" />
  <point x="412.0596" y="347.0276" pressure="0.5058824" time="1310684128456" name="point" id="26f0f023-8dcb-4ac8-996e-c6eedff8da2f" />
  <point x="412.0596" y="347.0276" pressure="0.3529412" time="1310684128464" name="point" id="01cd10c8-761e-4cb9-b321-8764a523de4f" />
  <point x="411.9818" y="346.2373" pressure="0.2" time="1310684128471" name="point" id="33d3c293-f6b8-4b8b-a3a3-4cb8a6f72c35" />
  <point x="412.0985" y="345.447" pressure="0.04313726" time="1310684128479" name="point" id="914ac649-a8c7-4f72-ae12-1e1c1ddcf73b" />
  <point x="410.9699" y="240.8465" pressure="0.1019608" time="1310684128784" name="point" id="3652244b-aba2-4b20-ad20-738dd648353f" />
  <point x="411.2034" y="239.6843" pressure="0.2392157" time="1310684128792" name="point" id="a091469d-d5dc-4c14-9bc5-91a7f3cb70ef" />
  <point x="411.9039" y="238.9404" pressure="0.3764706" time="1310684128799" name="point" id="adcbd0f1-a226-445b-a45c-a25624ad0f94" />
  <point x="412.9936" y="238.3361" pressure="0.5058824" time="1310684128807" name="point" id="58fbd20e-a8d3-4c2a-ae77-f9f3e2b7f1df" />
  <point x="414.6671" y="238.0571" pressure="0.5058824" time="1310684128814" name="point" id="0eb4551d-d224-4633-ad43-29a5534ca36c" />
  <point x="416.8854" y="237.9177" pressure="0.5019608" time="1310684128822" name="point" id="b4dfc615-830b-45f9-a6af-85ffccdf33cc" />
  <point x="419.882" y="238.0571" pressure="0.5019608" time="1310684128829" name="point" id="d3a2238a-a5b6-414c-ad1f-8d2a134f39a1" />
  <point x="423.3846" y="238.3826" pressure="0.5019608" time="1310684128837" name="point" id="2c58d4d4-0000-4fc5-980c-f9569924c00e" />
  <point x="427.432" y="238.894" pressure="0.5019608" time="1310684128844" name="point" id="daa39003-df12-44dc-8727-3ee6e421bf04" />
  <point x="431.8297" y="239.7307" pressure="0.5058824" time="1310684128852" name="point" id="b7bd7ebc-1380-441c-8cb8-cdfebc042522" />
  <point x="436.422" y="240.7535" pressure="0.5137255" time="1310684128859" name="point" id="0c22d7da-c4c3-437b-ac27-a8f4a9ce0dd9" />
  <point x="441.2478" y="242.1017" pressure="0.5176471" time="1310684128867" name="point" id="e9df7d72-6f25-402c-bedf-8f1f89063d04" />
  <point x="445.9958" y="243.6823" pressure="0.5294118" time="1310684128874" name="point" id="0025a303-4c4c-4c89-b646-fd1bf1e8e651" />
  <point x="450.8215" y="245.6349" pressure="0.5333334" time="1310684128882" name="point" id="d6b2ceff-2aa4-4205-a07f-f47ec24bac19" />
  <point x="455.2971" y="247.8663" pressure="0.5490196" time="1310684128889" name="point" id="7ecad475-b440-4c64-8c88-3862f9b75863" />
  <point x="459.5391" y="250.5162" pressure="0.5568628" time="1310684128897" name="point" id="23bb2271-0abf-433d-b97e-f74388426400" />
  <point x="463.3141" y="253.4915" pressure="0.5686275" time="1310684128904" name="point" id="a93b6b1e-fa2b-484d-a682-28c0a56a3d1e" />
  <point x="466.7777" y="256.8852" pressure="0.5764706" time="1310684128912" name="point" id="3f98af5e-02aa-4603-aa5b-7aa635ae5ea7" />
  <point x="469.6966" y="260.3254" pressure="0.5843138" time="1310684128919" name="point" id="40ad3778-242b-479c-a6a0-97d05b4389a8" />
  <point x="472.1484" y="264.2305" pressure="0.5921569" time="1310684128927" name="point" id="b2e7e6a1-e753-443a-b539-fc8030f27f96" />
  <point x="473.9386" y="268.3216" pressure="0.5960785" time="1310684128934" name="point" id="c4581b43-e240-4c0e-a8df-4a35f60fa970" />
  <point x="475.184" y="272.6451" pressure="0.6039216" time="1310684128942" name="point" id="3f15f9fe-b6d5-4167-9555-81e5396994fa" />
  <point x="475.7677" y="277.201" pressure="0.6078432" time="1310684128950" name="point" id="28fee5cd-529c-4106-8db9-9c8a12bf6af8" />
  <point x="475.7677" y="282.0358" pressure="0.6156863" time="1310684128957" name="point" id="a2aca2c1-eba9-487b-82a4-1949b6315bbd" />
  <point x="475.0283" y="286.8707" pressure="0.6235294" time="1310684128965" name="point" id="89ff8b6c-6ec5-4781-a257-c5fa1e03877b" />
  <point x="473.744" y="291.9845" pressure="0.627451" time="1310684128972" name="point" id="d35e0efc-5501-4239-99d1-5d0eac9b18f1" />
  <point x="471.7592" y="297.1913" pressure="0.6313726" time="1310684128980" name="point" id="19e843d3-7e48-421e-90c9-53fba2356d82" />
  <point x="469.3074" y="302.491" pressure="0.6392157" time="1310684128987" name="point" id="aeefd0d3-203d-4ce0-86e8-2c245db71a80" />
  <point x="466.2718" y="307.7908" pressure="0.6470588" time="1310684128995" name="point" id="c03e7e77-470d-4e90-812c-e9938880a339" />
  <point x="462.886" y="313.0905" pressure="0.6509804" time="1310684129002" name="point" id="e9a0d734-0480-497a-b707-ce5a55947879" />
  <point x="458.9942" y="318.1114" pressure="0.6588235" time="1310684129010" name="point" id="7bbfb0ad-884f-469d-950c-e3f78674cc18" />
  <point x="454.9079" y="322.9463" pressure="0.6588235" time="1310684129017" name="point" id="fdf69dcb-4ead-4d13-a843-915a235f51ee" />
  <point x="450.4713" y="327.5022" pressure="0.6666667" time="1310684129025" name="point" id="230de032-0707-44cf-9ca9-6a01a888c238" />
  <point x="445.8011" y="331.6862" pressure="0.6705883" time="1310684129032" name="point" id="d05fbe4e-fcb0-441d-b150-aab46565489d" />
  <point x="440.9754" y="335.4518" pressure="0.6705883" time="1310684129040" name="point" id="e2a1698d-b7f4-4077-9cc3-cc6a39cf77f2" />
  <point x="436.1107" y="338.7061" pressure="0.6705883" time="1310684129047" name="point" id="10beabcf-953f-4d60-8ae2-d157245e87a1" />
  <point x="431.1292" y="341.4024" pressure="0.6705883" time="1310684129055" name="point" id="02349f98-ede5-40b7-b938-2c0256785ab2" />
  <point x="426.2256" y="343.6339" pressure="0.6666667" time="1310684129062" name="point" id="c8078657-5d2e-4d79-83f1-e72bd41b83a3" />
  <point x="421.3998" y="345.3075" pressure="0.6666667" time="1310684129070" name="point" id="502071f4-f797-42c4-b243-04e36e6779a1" />
  <point x="416.8465" y="346.5627" pressure="0.654902" time="1310684129077" name="point" id="1ca07c8a-781f-46a5-8b9b-991b5889e000" />
  <point x="412.7601" y="347.3995" pressure="0.6509804" time="1310684129085" name="point" id="d42cee45-3aad-4e5b-905d-9da82691e03f" />
  <point x="409.0629" y="347.8179" pressure="0.6392157" time="1310684129092" name="point" id="df13bbac-c6f3-440e-9cae-b51106d2fa04" />
  <point x="406.1441" y="348.0969" pressure="0.6196079" time="1310684129100" name="point" id="d27ec993-04b4-4e1b-ada2-0869aeb6dde1" />
  <point x="403.4199" y="347.4925" pressure="0.5372549" time="1310684129107" name="point" id="2624d1d7-2dbc-486d-8f1b-28615c0aa7f7" />
  <point x="401.7464" y="347.1671" pressure="0.3843137" time="1310684129115" name="point" id="c196aa5d-744f-4bd9-a74a-26ba8ff02561" />
  <point x="400.6956" y="346.5162" pressure="0.227451" time="1310684129122" name="point" id="5f8d752c-229f-46b9-be0b-1f51bf612979" />
  <point x="400.5011" y="345.8189" pressure="0.07058824" time="1310684129130" name="point" id="625c214a-a1ce-4fa4-9924-10b8d6cccc90" />
  <shape type="substroke" name="substroke" id="d142ae27-de28-41dc-9c9f-f60f7266e93f" time="1310684127767" x="369.1724" y="228.6664" color="230436988" height="113.1545" width="34.16965" penTip="Ellipse" penWidth="2.00315" penHeight="2.00315" start="8ac0ad92-13d6-4918-a979-ed379ebf4756" end="41a4d93f-9833-4f4e-b8a1-0fde367878f5" source="InkSketch.canvasStrokeToSketchStroke" classification="Gate" connections="">
    <arg type="point">8ac0ad92-13d6-4918-a979-ed379ebf4756</arg>
    <arg type="point">56a0553a-f1dd-436e-96ad-c43a139652b8</arg>
    <arg type="point">0207b49d-0d63-4618-986d-4bd1dc44b079</arg>
    <arg type="point">1b7026ef-c82f-4d18-ae58-246cc377d875</arg>
    <arg type="point">5e25e478-5249-4a7e-b98d-34269ce4db56</arg>
    <arg type="point">8f13619d-52b4-486a-9069-e24053eb089c</arg>
    <arg type="point">04d1a15f-874d-4331-8452-958b55f391b4</arg>
    <arg type="point">c932b69f-dc21-43ae-9304-0070165cf38f</arg>
    <arg type="point">124ccc8b-5deb-4f18-a2ae-3dee9183d2ee</arg>
    <arg type="point">0d566dcc-8071-4d73-93d3-b2ce53c9f014</arg>
    <arg type="point">864f83c7-d6f7-454d-bc27-5054ae046c6a</arg>
    <arg type="point">88cc4dcc-2e92-413d-a3f1-57d916918a4a</arg>
    <arg type="point">b16f2160-0207-4dfc-8ed2-d677851c7728</arg>
    <arg type="point">aae2dcd2-bf04-4462-8edf-13a09e053e9a</arg>
    <arg type="point">cf9ea51d-76d3-4205-af62-2b06ba57c429</arg>
    <arg type="point">c7ae6848-c2c5-44b8-95a6-1102421166e5</arg>
    <arg type="point">9fe08c9b-38a9-4fdb-b9ab-19adef133396</arg>
    <arg type="point">5b988c8e-735f-463c-83db-7afc92ef803f</arg>
    <arg type="point">def14125-a4c2-420a-a869-ba42c82f6364</arg>
    <arg type="point">5b53db60-2035-49e3-8167-f8e3bb47330b</arg>
    <arg type="point">468f5237-92d4-46bc-85d1-e1314cd41474</arg>
    <arg type="point">dae99083-ceac-4eea-9786-63b9bc73f5c2</arg>
    <arg type="point">204893ad-24a3-4f29-b331-1620cd81f51a</arg>
    <arg type="point">486838c9-0db7-4c86-ab16-082a9567e62c</arg>
    <arg type="point">3cb90ef2-358a-4018-a89b-e187f753180a</arg>
    <arg type="point">5760e1e6-c06d-48fc-9e13-c1444bb28624</arg>
    <arg type="point">b7cb44db-1bee-4dca-9309-afc3b4ece21e</arg>
    <arg type="point">a66e5009-b191-492d-8d38-dbb50398bd2a</arg>
    <arg type="point">ddbeef94-e300-4766-bd36-2ca0687aeebc</arg>
    <arg type="point">4716ed65-6a05-485e-892d-7d14c87439bd</arg>
    <arg type="point">0ad5d0fc-8084-463f-9a94-7b3689fef78c</arg>
    <arg type="point">7d67a197-6452-49ff-ba2f-c7e266512c7e</arg>
    <arg type="point">963d8cb2-8d28-47dd-af75-17149c02c3a6</arg>
    <arg type="point">a32a3bd9-3820-451d-bfed-0847c84d027e</arg>
    <arg type="point">91b639ae-6e4a-4df0-b054-8cebf8bf8c64</arg>
    <arg type="point">450679cb-2b58-45d4-bbe1-9d063fe757aa</arg>
    <arg type="point">41a4d93f-9833-4f4e-b8a1-0fde367878f5</arg>
  </shape>
  <shape type="substroke" name="substroke" id="f4806c55-12c6-4530-bdc1-6c429d8e12cb" time="1310684128486" x="406.2609" y="235.4538" color="230436988" height="111.8063" width="25.25754" penTip="Ellipse" penWidth="2.00315" penHeight="2.00315" start="6b58b7c7-3e93-4e2f-b31e-788d957842db" end="914ac649-a8c7-4f72-ae12-1e1c1ddcf73b" source="InkSketch.canvasStrokeToSketchStroke" classification="Gate" connections="">
    <arg type="point">6b58b7c7-3e93-4e2f-b31e-788d957842db</arg>
    <arg type="point">76014bfe-f310-4067-8f8f-a506da1c7c4a</arg>
    <arg type="point">3197158c-0640-4656-ae56-44b8cb8a9bc3</arg>
    <arg type="point">ffb03809-4660-426f-8543-0148f4e50da5</arg>
    <arg type="point">db3d1105-f5f1-440e-95a2-36b06519a48b</arg>
    <arg type="point">3127eace-932a-4182-9d5c-5e7b42fabc66</arg>
    <arg type="point">f9e965d6-b195-4c45-a099-d8df1c719fb5</arg>
    <arg type="point">f9973aec-f22a-4d4e-85af-25299f559f3a</arg>
    <arg type="point">394fd5e9-ba1e-4ce1-8ed5-f8ed36eb5666</arg>
    <arg type="point">70908f5e-7562-46ee-b973-83466d7d1b3c</arg>
    <arg type="point">d5dc8a7b-a28a-467f-889d-fc6efe6c2057</arg>
    <arg type="point">5e1f6087-6419-4011-8f08-c5572fe559aa</arg>
    <arg type="point">8d992c52-fd53-4df6-8cbb-9a88cdadc5fa</arg>
    <arg type="point">e062116d-6f21-4243-bbc7-50bb52ff92c2</arg>
    <arg type="point">8a53321f-569b-48b4-8414-99ef0567657d</arg>
    <arg type="point">f31eb700-b939-4e45-9a8a-4498ad95430f</arg>
    <arg type="point">2dcb1266-27e3-460c-88b6-ca10757fcd07</arg>
    <arg type="point">71bf2983-71b8-42dc-8839-6431bb4ab685</arg>
    <arg type="point">eae13b6d-0cfb-4d3a-b5f2-bdacff4f73cb</arg>
    <arg type="point">10649d4c-692a-4cc1-8f71-1a8589548504</arg>
    <arg type="point">31139d15-d155-4fd0-8633-a9377fa648fd</arg>
    <arg type="point">bfb60657-80e1-4fab-a6c0-fa19d84bc4f8</arg>
    <arg type="point">84495c1f-3194-4e07-a603-68956e919786</arg>
    <arg type="point">1aac4ce3-f33f-49a1-bc68-ab1db3a596c1</arg>
    <arg type="point">2396b052-fdaf-412c-b4bf-7d20391acb72</arg>
    <arg type="point">8e5eeda2-0d3d-4d29-a6c1-129909a5fbbe</arg>
    <arg type="point">3876ac93-b5f0-4ede-9b7d-bc7c42258625</arg>
    <arg type="point">41041554-f31d-4acb-89c6-0de668f44c20</arg>
    <arg type="point">fa311aed-4412-4c08-a0ba-c7ec992eeb28</arg>
    <arg type="point">6bc83ab8-b08b-4c6d-b356-43d0c43800d8</arg>
    <arg type="point">2048c31e-e256-46f4-9f99-44b071dc7aa9</arg>
    <arg type="point">54cfa7d6-7037-437f-a497-42673928121e</arg>
    <arg type="point">e02695e8-1c1f-4a6d-9206-0ea28e6a432a</arg>
    <arg type="point">0f5b3433-e00f-4912-b4d1-7b6b60b47dc2</arg>
    <arg type="point">1a4b4ef6-109c-4097-8536-fbd562ad5b92</arg>
    <arg type="point">26f0f023-8dcb-4ac8-996e-c6eedff8da2f</arg>
    <arg type="point">01cd10c8-761e-4cb9-b321-8764a523de4f</arg>
    <arg type="point">33d3c293-f6b8-4b8b-a3a3-4cb8a6f72c35</arg>
    <arg type="point">914ac649-a8c7-4f72-ae12-1e1c1ddcf73b</arg>
  </shape>
  <shape type="substroke" name="substroke" id="fc2d5c18-a64c-4fb5-91c2-1e54914688da" time="1310684129137" x="400.5011" y="237.9177" color="230436988" height="110.1792" width="75.26663" penTip="Ellipse" penWidth="2.00315" penHeight="2.00315" start="3652244b-aba2-4b20-ad20-738dd648353f" end="625c214a-a1ce-4fa4-9924-10b8d6cccc90" source="InkSketch.canvasStrokeToSketchStroke" classification="Gate" connections="">
    <arg type="point">3652244b-aba2-4b20-ad20-738dd648353f</arg>
    <arg type="point">a091469d-d5dc-4c14-9bc5-91a7f3cb70ef</arg>
    <arg type="point">adcbd0f1-a226-445b-a45c-a25624ad0f94</arg>
    <arg type="point">58fbd20e-a8d3-4c2a-ae77-f9f3e2b7f1df</arg>
    <arg type="point">0eb4551d-d224-4633-ad43-29a5534ca36c</arg>
    <arg type="point">b4dfc615-830b-45f9-a6af-85ffccdf33cc</arg>
    <arg type="point">d3a2238a-a5b6-414c-ad1f-8d2a134f39a1</arg>
    <arg type="point">2c58d4d4-0000-4fc5-980c-f9569924c00e</arg>
    <arg type="point">daa39003-df12-44dc-8727-3ee6e421bf04</arg>
    <arg type="point">b7bd7ebc-1380-441c-8cb8-cdfebc042522</arg>
    <arg type="point">0c22d7da-c4c3-437b-ac27-a8f4a9ce0dd9</arg>
    <arg type="point">e9df7d72-6f25-402c-bedf-8f1f89063d04</arg>
    <arg type="point">0025a303-4c4c-4c89-b646-fd1bf1e8e651</arg>
    <arg type="point">d6b2ceff-2aa4-4205-a07f-f47ec24bac19</arg>
    <arg type="point">7ecad475-b440-4c64-8c88-3862f9b75863</arg>
    <arg type="point">23bb2271-0abf-433d-b97e-f74388426400</arg>
    <arg type="point">a93b6b1e-fa2b-484d-a682-28c0a56a3d1e</arg>
    <arg type="point">3f98af5e-02aa-4603-aa5b-7aa635ae5ea7</arg>
    <arg type="point">40ad3778-242b-479c-a6a0-97d05b4389a8</arg>
    <arg type="point">b2e7e6a1-e753-443a-b539-fc8030f27f96</arg>
    <arg type="point">c4581b43-e240-4c0e-a8df-4a35f60fa970</arg>
    <arg type="point">3f15f9fe-b6d5-4167-9555-81e5396994fa</arg>
    <arg type="point">28fee5cd-529c-4106-8db9-9c8a12bf6af8</arg>
    <arg type="point">a2aca2c1-eba9-487b-82a4-1949b6315bbd</arg>
    <arg type="point">89ff8b6c-6ec5-4781-a257-c5fa1e03877b</arg>
    <arg type="point">d35e0efc-5501-4239-99d1-5d0eac9b18f1</arg>
    <arg type="point">19e843d3-7e48-421e-90c9-53fba2356d82</arg>
    <arg type="point">aeefd0d3-203d-4ce0-86e8-2c245db71a80</arg>
    <arg type="point">c03e7e77-470d-4e90-812c-e9938880a339</arg>
    <arg type="point">e9a0d734-0480-497a-b707-ce5a55947879</arg>
    <arg type="point">7bbfb0ad-884f-469d-950c-e3f78674cc18</arg>
    <arg type="point">fdf69dcb-4ead-4d13-a843-915a235f51ee</arg>
    <arg type="point">230de032-0707-44cf-9ca9-6a01a888c238</arg>
    <arg type="point">d05fbe4e-fcb0-441d-b150-aab46565489d</arg>
    <arg type="point">e2a1698d-b7f4-4077-9cc3-cc6a39cf77f2</arg>
    <arg type="point">10beabcf-953f-4d60-8ae2-d157245e87a1</arg>
    <arg type="point">02349f98-ede5-40b7-b938-2c0256785ab2</arg>
    <arg type="point">c8078657-5d2e-4d79-83f1-e72bd41b83a3</arg>
    <arg type="point">502071f4-f797-42c4-b243-04e36e6779a1</arg>
    <arg type="point">1ca07c8a-781f-46a5-8b9b-991b5889e000</arg>
    <arg type="point">d42cee45-3aad-4e5b-905d-9da82691e03f</arg>
    <arg type="point">df13bbac-c6f3-440e-9cae-b51106d2fa04</arg>
    <arg type="point">d27ec993-04b4-4e1b-ada2-0869aeb6dde1</arg>
    <arg type="point">2624d1d7-2dbc-486d-8f1b-28615c0aa7f7</arg>
    <arg type="point">c196aa5d-744f-4bd9-a74a-26ba8ff02561</arg>
    <arg type="point">5f8d752c-229f-46b9-be0b-1f51bf612979</arg>
    <arg type="point">625c214a-a1ce-4fa4-9924-10b8d6cccc90</arg>
  </shape>
  <shape type="stroke" name="stroke" id="a2be2a15-5bb6-402f-b334-881c2e73ba4f" time="1310684127767" x="369.1724" y="228.6664" height="113.1545" width="34.16965" start="d142ae27-de28-41dc-9c9f-f60f7266e93f" end="d142ae27-de28-41dc-9c9f-f60f7266e93f" source="Converter" connections="">
    <arg type="substroke">d142ae27-de28-41dc-9c9f-f60f7266e93f</arg>
  </shape>
  <shape type="stroke" name="stroke" id="d22ff014-86c6-458e-9761-a353e8ff0d7b" time="1310684128486" x="406.2609" y="235.4538" height="111.8063" width="25.25754" start="f4806c55-12c6-4530-bdc1-6c429d8e12cb" end="f4806c55-12c6-4530-bdc1-6c429d8e12cb" source="Converter" connections="">
    <arg type="substroke">f4806c55-12c6-4530-bdc1-6c429d8e12cb</arg>
  </shape>
  <shape type="stroke" name="stroke" id="1cd6da1a-00d4-46dc-b3ea-24d6c0555e67" time="1310684129137" x="400.5011" y="237.9177" height="110.1792" width="75.26663" start="fc2d5c18-a64c-4fb5-91c2-1e54914688da" end="fc2d5c18-a64c-4fb5-91c2-1e54914688da" source="Converter" connections="">
    <arg type="substroke">fc2d5c18-a64c-4fb5-91c2-1e54914688da</arg>
  </shape>
  <shape type="XOR" name="XOR_0" id="56378683-ab37-4216-8d2f-0eab1f04385d" time="1310684129137" x="369.1724" y="228.6664" height="119.4305" width="106.5953" orientation="0" start="d142ae27-de28-41dc-9c9f-f60f7266e93f" end="fc2d5c18-a64c-4fb5-91c2-1e54914688da" classification="Gate" connections="">
    <arg type="substroke">d142ae27-de28-41dc-9c9f-f60f7266e93f</arg>
    <arg type="substroke">f4806c55-12c6-4530-bdc1-6c429d8e12cb</arg>
    <arg type="substroke">fc2d5c18-a64c-4fb5-91c2-1e54914688da</arg>
  </shape>
  <circuit inputs="" outputs="">
    <behavior>
      <input />
      <output />
    </behavior>
  </circuit>
</sketch>